oisin/__init__.py
oisin/corpus.py
oisin/main.py
oisin/poetry.py
oisin/wfc.py
oisin-0.1.1.dist-info/LICENSE.md
oisin-0.1.1.dist-info/METADATA
oisin-0.1.1.dist-info/WHEEL
oisin-0.1.1.dist-info/top_level.txt
oisin-0.1.1.dist-info/RECORD
