Metadata-Version: 2.1
Name: oisin
Version: 0.1.1
Summary: This is inpv's fork of mewo2's code for performing the WaveFunctionCollapse algorithm on poems. It mashes up sentence fragments from a given corpus to produce poems with fixed metric forms.
Author-email: mewo2 & inpv <inpv@protonmail.ch>
Project-URL: Homepage, https://github.com/pypa/oisin
Project-URL: Bug Tracker, https://github.com/pypa/oisin/issues
Classifier: Programming Language :: Python :: 3
Classifier: License :: OSI Approved :: MIT License
Classifier: Operating System :: OS Independent
Requires-Python: >=3.10
License-File: LICENSE.md
